__init__.py
bank_customer_generator.py
bank_customer_generator-1.0.0.dist-info/licenses/LICENSE.txt
bank_customer_generator-1.0.0.dist-info/METADATA
bank_customer_generator-1.0.0.dist-info/WHEEL
bank_customer_generator-1.0.0.dist-info/entry_points.txt
bank_customer_generator-1.0.0.dist-info/top_level.txt
bank_customer_generator-1.0.0.dist-info/RECORD
